foxhelpers/__init__.py
foxhelpers/dist_helper.py
foxhelpers/foxConfig/__init__.py
foxhelpers/foxConfig/argparser/__init__.py
foxhelpers/foxConfig/argparser/parser.py
foxhelpers/foxConfig/omega_config/__init__.py
foxhelpers/foxConfig/omega_config/omega_parser.py
foxhelpers/foxIO/__init__.py
foxhelpers/foxIO/interface.py
foxhelpers/foxIO/modelart.py
foxhelpers/foxMetrics/__init__.py
foxhelpers/foxMetrics/averagemeter.py
foxhelpers/foxMetrics/meter_interface.py
foxhelpers/foxMetrics/metric.py
foxhelpers/foxMetrics/pprint.py
foxhelpers/foxMetrics/storage_interface.py
foxhelpers/foxMetrics/utils.py
foxhelpers-1.1.7.dist-info/METADATA
foxhelpers-1.1.7.dist-info/WHEEL
foxhelpers-1.1.7.dist-info/top_level.txt
foxhelpers-1.1.7.dist-info/RECORD
