Metadata-Version: 2.1
Name: foxhelpers
Version: 1.1.7
Summary: metrics for decoupled training
Home-page: 
Author: jizong
Author-email: jizong.peng.ca@gmail.com
Requires-Python: >3.6.0
Requires-Dist: loguru
Requires-Dist: termcolor
Requires-Dist: pandas
Requires-Dist: numpy
Requires-Dist: omegaconf
Requires-Dist: prettytable
Requires-Dist: torch
Requires-Dist: ipdb
